playwbot/Playwbot.py
playwbot/__init__.py
playwbot/src/__init__.py
playwbot/src/browser.py
playwbot/src/context.py
playwbot/src/handle.py
playwbot/src/page.py
playwbot/src/utils.py
playwbot-0.3.0.dist-info/WHEEL
playwbot-0.3.0.dist-info/METADATA
playwbot-0.3.0.dist-info/RECORD
