Metadata-Version: 2.1
Name: playwbot
Version: 0.3.0
Summary: RobotFramework wrapper of Playwright-Python
Home-page: https://radekbednarik.github.io/playwbot/
License: MIT
Keywords: playwright,playwbot,playwright-python,test-automation,robot-framework
Author: radekBednarik
Author-email: radek.bednarik@tesena.com
Requires-Python: >=3.9,<4.0
Classifier: Development Status :: 4 - Beta
Classifier: Environment :: Web Environment
Classifier: Framework :: Robot Framework
Classifier: Framework :: Robot Framework :: Library
Classifier: Intended Audience :: Developers
Classifier: License :: OSI Approved :: MIT License
Classifier: Operating System :: MacOS
Classifier: Operating System :: Microsoft :: Windows
Classifier: Operating System :: POSIX :: Linux
Classifier: Programming Language :: Python :: 3
Classifier: Programming Language :: Python :: 3.9
Classifier: Topic :: Education :: Testing
Requires-Dist: playwright (>=1.12.1,<2.0.0)
Requires-Dist: robotframework (>=4.0.3,<5.0.0)
Project-URL: Documentation, https://radekbednarik.github.io/playwbot/
Project-URL: Repository, https://github.com/radekBednarik/playwbot
